{
  "async.css": {
    "file": "_app/immutable/assets/async-6417fb07.css",
    "src": "async.css"
  },
  "src/routes/tictaccup/+page.css": {
    "file": "_app/immutable/assets/_page-db31e217.css",
    "src": "src/routes/tictaccup/+page.css"
  },
  "src/routes/tictactoe/+page.css": {
    "file": "_app/immutable/assets/_page-1f79d234.css",
    "src": "src/routes/tictactoe/+page.css"
  },
  "node_modules/@sveltejs/kit/src/runtime/components/error.svelte": {
    "file": "_app/immutable/components/error.svelte-36cda0d5.js",
    "src": "node_modules/@sveltejs/kit/src/runtime/components/error.svelte",
    "isEntry": true,
    "imports": [
      "_index-e565ab33.js",
      "_singletons-5766cb16.js"
    ]
  },
  "src/routes/+page.svelte": {
    "file": "_app/immutable/components/pages/_page.svelte-922dbb9e.js",
    "src": "src/routes/+page.svelte",
    "isEntry": true,
    "imports": [
      "_index-e565ab33.js"
    ]
  },
  ".svelte-kit/generated/nodes/4.js": {
    "file": "_app/immutable/chunks/4-d4846c16.js",
    "src": ".svelte-kit/generated/nodes/4.js",
    "isDynamicEntry": true,
    "imports": [
      "src/routes/tictactoe/+page.svelte"
    ]
  },
  ".svelte-kit/generated/nodes/3.js": {
    "file": "_app/immutable/chunks/3-a38af62d.js",
    "src": ".svelte-kit/generated/nodes/3.js",
    "isDynamicEntry": true,
    "imports": [
      "src/routes/tictaccup/+page.svelte"
    ]
  },
  "_singletons-5766cb16.js": {
    "file": "_app/immutable/chunks/singletons-5766cb16.js",
    "imports": [
      "_index-bcec075a.js"
    ]
  },
  "_index-e565ab33.js": {
    "file": "_app/immutable/chunks/index-e565ab33.js"
  },
  "_index-bcec075a.js": {
    "file": "_app/immutable/chunks/index-bcec075a.js",
    "imports": [
      "_index-e565ab33.js"
    ]
  },
  "_preload-helper-41c905a7.js": {
    "file": "_app/immutable/chunks/preload-helper-41c905a7.js"
  },
  "src/routes/+layout.svelte": {
    "file": "_app/immutable/components/pages/_layout.svelte-b1f72c58.js",
    "src": "src/routes/+layout.svelte",
    "isEntry": true,
    "imports": [
      "_index-e565ab33.js"
    ]
  },
  ".svelte-kit/generated/nodes/0.js": {
    "file": "_app/immutable/chunks/0-d074453c.js",
    "src": ".svelte-kit/generated/nodes/0.js",
    "isDynamicEntry": true,
    "imports": [
      "__layout-da46b06b.js",
      "src/routes/+layout.svelte"
    ]
  },
  ".svelte-kit/generated/nodes/1.js": {
    "file": "_app/immutable/chunks/1-a2c8961e.js",
    "src": ".svelte-kit/generated/nodes/1.js",
    "isDynamicEntry": true,
    "imports": [
      "node_modules/@sveltejs/kit/src/runtime/components/error.svelte"
    ]
  },
  ".svelte-kit/generated/nodes/2.js": {
    "file": "_app/immutable/chunks/2-b5dcb5e4.js",
    "src": ".svelte-kit/generated/nodes/2.js",
    "isDynamicEntry": true,
    "imports": [
      "src/routes/+page.svelte"
    ]
  },
  "_async-39953546.js": {
    "file": "_app/immutable/chunks/async-39953546.js",
    "imports": [
      "_index-e565ab33.js",
      "_index-bcec075a.js"
    ],
    "css": [
      "_app/immutable/assets/async-6417fb07.css"
    ]
  },
  "node_modules/@sveltejs/kit/src/runtime/client/start.js": {
    "file": "_app/immutable/start-11820b68.js",
    "src": "node_modules/@sveltejs/kit/src/runtime/client/start.js",
    "isEntry": true,
    "imports": [
      "_index-e565ab33.js",
      "_singletons-5766cb16.js",
      "_preload-helper-41c905a7.js"
    ],
    "dynamicImports": [
      ".svelte-kit/generated/nodes/0.js",
      ".svelte-kit/generated/nodes/1.js",
      ".svelte-kit/generated/nodes/2.js",
      ".svelte-kit/generated/nodes/3.js",
      ".svelte-kit/generated/nodes/4.js"
    ]
  },
  "src/routes/tictaccup/+page.svelte": {
    "file": "_app/immutable/components/pages/tictaccup/_page.svelte-1b029079.js",
    "src": "src/routes/tictaccup/+page.svelte",
    "isEntry": true,
    "imports": [
      "_index-e565ab33.js",
      "_async-39953546.js",
      "_index-bcec075a.js"
    ],
    "css": [
      "_app/immutable/assets/_page-db31e217.css"
    ]
  },
  "src/routes/+layout.js": {
    "file": "_app/immutable/modules/pages/_layout.js-9cbb603b.js",
    "src": "src/routes/+layout.js",
    "isEntry": true,
    "imports": [
      "__layout-da46b06b.js"
    ]
  },
  "src/routes/tictactoe/+page.svelte": {
    "file": "_app/immutable/components/pages/tictactoe/_page.svelte-203ee6f7.js",
    "src": "src/routes/tictactoe/+page.svelte",
    "isEntry": true,
    "imports": [
      "_index-e565ab33.js",
      "_async-39953546.js",
      "_preload-helper-41c905a7.js"
    ],
    "dynamicImports": [
      "_p5.min-7dea8225.js"
    ],
    "css": [
      "_app/immutable/assets/_page-1f79d234.css"
    ]
  },
  "__layout-da46b06b.js": {
    "file": "_app/immutable/chunks/_layout-da46b06b.js"
  },
  "_p5.min-7dea8225.js": {
    "file": "_app/immutable/chunks/p5.min-7dea8225.js",
    "isDynamicEntry": true
  }
}